.gitignore
MANIFEST.in
README.rst
bootstrap.py
buildout.cfg
collective.linguaanalytics-configure.zcml
gitignore
jenkins.cfg
setup.py
collective/__init__.py
collective.linguaanalytics.egg-info/PKG-INFO
collective.linguaanalytics.egg-info/SOURCES.txt
collective.linguaanalytics.egg-info/dependency_links.txt
collective.linguaanalytics.egg-info/entry_points.txt
collective.linguaanalytics.egg-info/namespace_packages.txt
collective.linguaanalytics.egg-info/not-zip-safe
collective.linguaanalytics.egg-info/requires.txt
collective.linguaanalytics.egg-info/top_level.txt
collective/linguaanalytics/__init__.py
collective/linguaanalytics/configure.zcml
collective/linguaanalytics/controlpanel.py
collective/linguaanalytics/interfaces.py
collective/linguaanalytics/rebuild_i18n.sh
collective/linguaanalytics/testing.py
collective/linguaanalytics/locales/collective.linguaanalytics.pot
collective/linguaanalytics/locales/en/LC_MESSAGES/collective.linguaanalytics.po
collective/linguaanalytics/locales/fr/LC_MESSAGES/collective.linguaanalytics.po
collective/linguaanalytics/profiles/default/browserlayer.xml
collective/linguaanalytics/profiles/default/controlpanel.xml
collective/linguaanalytics/profiles/default/metadata.xml
collective/linguaanalytics/profiles/default/registry.xml
collective/linguaanalytics/tests/__init__.py
collective/linguaanalytics/tests/base.py
collective/linguaanalytics/tests/test_integration_trackingviewlet.py
collective/linguaanalytics/tests/test_setup.py
collective/linguaanalytics/tests/test_unittest__trackingviewlet.py
collective/linguaanalytics/tests/utils.py
collective/linguaanalytics/upgrades/__init__.py
collective/linguaanalytics/upgrades/configure.zcml
collective/linguaanalytics/upgrades/v1000_to_1001.py
collective/linguaanalytics/viewlets/__init__.py
collective/linguaanalytics/viewlets/analytics.py
collective/linguaanalytics/viewlets/configure.zcml
docs/HISTORY.txt