Metadata-Version: 1.0
Name: collective.linguaanalytics
Version: 1.0
Summary: Google Analytics specialized for MultiLanguage sites
Home-page: https://github.com/toutpt/collective.linguaanalytics
Author: JeanMichel FRANCOIS aka toutpt
Author-email: toutpt@gmail.com
License: GPL
Keywords: plone analytics multilanguage
Platform: UNKNOWN
Classifier: Programming Language :: Python
Classifier: Framework :: Plone
Classifier: Framework :: Plone :: 4.0
Classifier: Framework :: Plone :: 4.1
Classifier: Framework :: Plone :: 4.2
